seqtag_keras/__init__.py
seqtag_keras/callbacks.py
seqtag_keras/layers.py
seqtag_keras/models.py
seqtag_keras/preprocessing.py
seqtag_keras/tagger.py
seqtag_keras/trainer.py
seqtag_keras/utils.py
seqtag_keras/wrapper.py
seqtag_keras-1.0.6.dist-info/LICENSE
seqtag_keras-1.0.6.dist-info/METADATA
seqtag_keras-1.0.6.dist-info/WHEEL
seqtag_keras-1.0.6.dist-info/top_level.txt
seqtag_keras-1.0.6.dist-info/RECORD
