Metadata-Version: 2.1
Name: seqtag-keras
Version: 1.0.6
Summary: Easy to use BiLSTM+CRF sequence tagging for text.
Home-page: https://github.com/bedapudi6788/seqtag-keras
Author: BEDAPUDI PRANEETH
Author-email: praneethbedapudi@gmail.com
License: MIT
Platform: UNKNOWN
Classifier: License :: OSI Approved :: MIT License
Classifier: Programming Language :: Python
Classifier: Programming Language :: Python :: 2.6
Classifier: Programming Language :: Python :: 2.7
Classifier: Programming Language :: Python :: 3
Classifier: Programming Language :: Python :: 3.3
Classifier: Programming Language :: Python :: 3.4
Classifier: Programming Language :: Python :: 3.5
Classifier: Programming Language :: Python :: 3.6
Classifier: Programming Language :: Python :: Implementation :: CPython
Classifier: Programming Language :: Python :: Implementation :: PyPy
Requires-Python: >=3.5.0
Requires-Dist: Keras (<=2.3.1)
Requires-Dist: scikit-learn
Requires-Dist: seqeval (==0.0.3)
